Metadata-Version: 2.1
Name: fmg
Version: 0.3.0
Summary: Fast Memory Graphics for big image, use like OpenSlide
Home-page: https://github.com/khtao/fmg
Author: khtao
Author-email: khtao@live.cn
License: MIT
Platform: UNKNOWN
Classifier: License :: OSI Approved :: MIT License
Classifier: Programming Language :: Python
Classifier: Programming Language :: Python :: 3
Classifier: Programming Language :: Python :: 3.6
Classifier: Programming Language :: Python :: Implementation :: CPython
Classifier: Programming Language :: Python :: Implementation :: PyPy
Requires-Python: >=3.6.0
License-File: LICENSE
